{
  "dokument_id": "cd4f4545-5e0b-55c7-8fc4-e8e2ae44d9db",
  "doc_type": "case_minutes",
  "kommune": 4601,
  "tittel": "Saksprotokoll , 17042024, Sak 59/24, Bellevuebakken boliger. 2. gangsbehandling av reguleringsplan",
  "url": "https://bergen.kommune.no/politikere-utvalg/api/fil/bk360/10321057/Innstilling-vedtak-Bellevuebakken-boliger-2-gangsbehandling-av-reguleringsplan",
  "tekst": "Bellevuebakken boliger. 2. gangsbehandling av reguleringsplan Eldrer\u00e5det behandlet saken i m\u00f8tet 17.04.2024 sak 59/24 og fattet f\u00f8lgende vedtak: F\u00f8lgende brev sendes til utvalg for milj\u00f8 og byutvikling Merknad 1: 2-3 av einingane b\u00f8r \u00f8yremerkjast eldre. Merknad 2: Det m\u00e5 legges opp til bedre parkeringsdekning Begrunnelse for forslag / merknader: Eldrer\u00e5det tek reguleringsplanen til orientering, og har elles desse merknadene: R\u00e5det meiner 2-3 av desse einingane b\u00f8r \u00f8yremerkjast eldre (jf reforma Bu trygt heime). Dette heng saman med at vi meiner kommunen m\u00e5 arbeida m\u00e5lretta for \u00e5 skaffa eldre tenlege boligar, og dette gjeld ikkje minst i h\u00f8ve til den omfattande private boligutbygginga i Bergen. Omr\u00e5det er bratt og med d\u00e5rlig kollektivdekning. Skal eldre kunne bosette seg her er det n\u00f8dvendig med bedre mulighet for parkering. "
}