{
  "dokument_id": "75dfb312-b8b0-5ee8-bcd5-157254c73a32",
  "doc_type": "case_attachment",
  "kommune": 4601,
  "tittel": "Uttalelse fra Den norske kirke, datert 27.01.2022",
  "url": "https://bergen.kommune.no/politikere-utvalg/api/fil/bk360/9464421/Uttalelse-fra-Den-norske-kirke-datert-27-01-2022",
  "tekst": "Fra: Ingrid HauglandLis\u00f8y<ih889@kirken.no> Sendt: torsdag27. januar 202213:58 Til: Postmottakplanogbygg Emne: 22/00701-1- Anmodningom uttalelsetil s\u00f8knadspliktigtiltak - Gnr 13 - Bnr 384 - Kirkevegen18 Vi har ingenmerknadertil tiltaket. Mvh Ingrid HauglandLis\u00f8y Juridiskr\u00e5dgiver Marken 34, 5017 Bergen Tlf 93 06 04 97 F\u00f8lgossp\u00e5 Facebook F\u00f8lgmed p\u00e5 v\u00e5r hjemmeside "
}