{
  "dokument_id": "f714ea68-2758-55f0-9c05-e57184449372",
  "doc_type": "case_attachment",
  "kommune": 4601,
  "tittel": "Kvittering for nabovarsel",
  "url": "https://bergen.kommune.no/politikere-utvalg/api/fil/bk360/8564090/Kvittering-for-nabovarsel",
  "tekst": "Kvittering for nabovarsel S\u00f8ker: Grieg Arkitekter AS Altinnreferanse: AR543312252 Eiendom/byggested Adresse: Strimmelen 3, 7, 11, 15, 19, 23, 27 og 31. Land\u00e5slien 17, 19, 21, 25 og 27 , 5097 Bergen Kommune: Bergen G\u00e5rdsnr.: Bruksnr.: Festenr.: Seksjonsnr.: 161 1037 0 0 F\u00f8lgende vedlegg er sendt med nabovarselet: Vedleggstype: Filnavn: Nabovarsel Nabovarsel.pdf Situasjonsplan D-2 Situasjonsplan - nord.pdf Situasjonsplan D-3 Situasjonsplan - s\u00f8r.pdf Situasjonsplan D-1 Situasjonsplan - hele.pdf TegningNyFasade E-4 3D-skisser bygg C.pdf TegningNyFasade E-2C Fasader etter endring bygg C.pdf TegningNyPlan E-2A Kjellerplan, snitt og fasade etter bygg A.pdf Dispensasjonssoeknad B-1 dispensasjonss\u00f8knad bygg A.pdf Dispensasjonssoeknad B-1 dispensasjonss\u00f8knad bygg C.pdf TegningEksisterendeFasade E-1C Fasader eksisterende bygg C.pdf TegningEksisterendePlan E-1A Kjellerplan, snitt og fasade eksisterende bygg A.pdf F\u00f8lgende naboer har f\u00e5tt sending av nabovarsel med tilh\u00f8rende vedlegg: Eier/fester av naboeiendom: SAMEIET VEIVESENETS BYGGELAG Adresse: G\u00e5rdsnr.: Bruksnr.: Festenr.: Seksjonsnr.: Land\u00e5slien 33A, 5097 BERGEN 161 850 0 0 Nabovarsel sendt via: Fellestjenester Bygg Nabovarsel sendt: 22.03.2023 15.40.28 Eier/fester av naboeiendom: SAMEIET NATTLANDSVEIEN 84 Adresse: G\u00e5rdsnr.: Bruksnr.: Festenr.: Seksjonsnr.: Strandgaten 196, 5004 BERGEN 161 1018 0 0 Nabovarsel sendt via: Fellestjenester Bygg Nabovarsel sendt: 22.03.2023 15.40.36 Eier/fester av naboeiendom: VESTLAND FYLKESKOMMUNE Adresse: G\u00e5rdsnr.: Bruksnr.: Festenr.: Seksjonsnr.: 160 447 0 0 Nabovarsel sendt via: Fellestjenester Bygg Nabovarsel sendt: 22.03.2023 15.40.42 Eier/fester av naboeiendom: AIVOG AS Adresse: G\u00e5rdsnr.: Bruksnr.: Festenr.: Seksjonsnr.: Nattlandsveien 85, 5094 BERGEN 160 470 0 1 Nattlandsveien 85, 5094 BERGEN 160 470 0 2 Nabovarsel sendt via: Fellestjenester Bygg Nabovarsel sendt: 22.03.2023 15.40.50 Eier/fester av naboeiendom: Natlandsv 87 AS Adresse: G\u00e5rdsnr.: Bruksnr.: Festenr.: Seksjonsnr.: Nattlandsveien 87A, 5094 BERGEN 160 471 0 0 Nabovarsel sendt via: Fellestjenester Bygg Nabovarsel sendt: 22.03.2023 15.40.57 Eier/fester av naboeiendom: BERGEN KOMMUNE Adresse: G\u00e5rdsnr.: Bruksnr.: Festenr.: Seksjonsnr.: 160 750 0 0 161 795 0 0 161 847 0 0 Erleveien 60A, 5097 BERGEN 161 987 0 0 Nattlandsveien 92A, 5094 BERGEN 161 1021 0 0 Strimmelen 3, 5097 BERGEN 161 1037 0 0 Land\u00e5slien 15, 5097 BERGEN 161 1038 0 0 Nabovarsel sendt via: Fellestjenester Bygg Nabovarsel sendt: 22.03.2023 15.41.08 Eier/fester av naboeiendom: \u00c5SE HAUG Adresse: G\u00e5rdsnr.: Bruksnr.: Festenr.: Seksjonsnr.: Land\u00e5slien 33, 5097 BERGEN 161 849 0 0 Nabovarsel sendt via: Fellestjenester Bygg Nabovarsel sendt: 22.03.2023 15.41.17 Eier/fester av naboeiendom: HEGE JEANETTE BRATLAND Adresse: G\u00e5rdsnr.: Bruksnr.: Festenr.: Seksjonsnr.: Land\u00e5slien 34, 5097 BERGEN 161 851 0 0 Nabovarsel sendt via: Fellestjenester Bygg Nabovarsel sendt: 22.03.2023 15.41.23 Eier/fester av naboeiendom: STEIN MORTEN BRATLAND Adresse: G\u00e5rdsnr.: Bruksnr.: Festenr.: Seksjonsnr.: Land\u00e5slien 34, 5097 BERGEN 161 851 0 0 Nabovarsel sendt via: Fellestjenester Bygg Nabovarsel sendt: 22.03.2023 15.41.30 Eier/fester av naboeiendom: BERGEN KOMMUNE BYMILJ\u00d8ETATEN Adresse: G\u00e5rdsnr.: Bruksnr.: Festenr.: Seksjonsnr.: 161 923 0 0 161 1034 0 0 Nabovarsel sendt via: Fellestjenester Bygg Nabovarsel sendt: 22.03.2023 15.41.37 Eier/fester av naboeiendom: Erlev 60 X AS Adresse: G\u00e5rdsnr.: Bruksnr.: Festenr.: Seksjonsnr.: Erleveien 60A, 5097 BERGEN 161 987 0 0 Nabovarsel sendt via: Fellestjenester Bygg Nabovarsel sendt: 22.03.2023 15.41.43 Eier/fester av naboeiendom: Natlandsveien Borettslag Adresse: G\u00e5rdsnr.: Bruksnr.: Festenr.: Seksjonsnr.: Nattlandsveien 92A, 5094 BERGEN 161 1021 0 0 Nabovarsel sendt via: Fellestjenester Bygg Nabovarsel sendt: 22.03.2023 15.41.49 Eier/fester av naboeiendom: STRIMMELEN N\u00c6RINGSBYGG AS Adresse: G\u00e5rdsnr.: Bruksnr.: Festenr.: Seksjonsnr.: Strimmelen 1, 5097 BERGEN 161 1035 0 0 Nabovarsel sendt via: Fellestjenester Bygg Nabovarsel sendt: 22.03.2023 15.41.55 Eier/fester av naboeiendom: Strimmelen Borettslag Adresse: G\u00e5rdsnr.: Bruksnr.: Festenr.: Seksjonsnr.: Land\u00e5slien 15, 5097 BERGEN 161 1038 0 0 Nabovarsel sendt via: Fellestjenester Bygg Nabovarsel sendt: 22.03.2023 15.42.02 Eier/fester av naboeiendom: INGER JOHANNE JENSEN Adresse: G\u00e5rdsnr.: Bruksnr.: Festenr.: Seksjonsnr.: Erleveien 58C, 5097 BERGEN 161 1241 0 0 Nabovarsel sendt via: Fellestjenester Bygg Nabovarsel sendt: 22.03.2023 15.42.09 Eier/fester av naboeiendom: GEIR-MAGNE HAUGLAND Adresse: G\u00e5rdsnr.: Bruksnr.: Festenr.: Seksjonsnr.: Erleveien 58D, 5097 BERGEN 161 1242 0 0 Nabovarsel sendt via: Fellestjenester Bygg Nabovarsel sendt: 22.03.2023 15.42.16 Eier/fester av naboeiendom: THEA NGUYEN Adresse: G\u00e5rdsnr.: Bruksnr.: Festenr.: Seksjonsnr.: Erleveien 58E, 5097 BERGEN 161 1243 0 0 Nabovarsel sendt via: Fellestjenester Bygg Nabovarsel sendt: 22.03.2023 15.42.22 "
}